[
{"id":"28109","county":"Pearl River County","measure":"10green","y1":1980,"y2":2021,"data":[0,0,0,0,0,0,0,0,0,0,0,0,0,0,0,0,0,0,0,0,0,0,0,0,0,0,0,0,0,0,0,0,0,0,0,0,0,0,0,0,0,0]},
{"id":"28109","county":"Pearl River County","measure":"aqi","y1":1980,"y2":2021,"data":[null,null,null,null,null,null,null,null,null,null,null,null,null,null,null,null,null,null,null,null,null,null,null,null,null,null,null,null,null,null,null,null,null,null,null,null,null,null,null,null,null,null]},
{"id":"28109","county":"Pearl River County","measure":"ozone","y1":1980,"y2":2021,"data":[null,null,null,null,null,null,null,null,null,null,null,null,null,null,null,null,null,null,null,null,null,null,null,null,null,null,null,null,null,null,null,null,null,null,null,null,null,null,null,null,null,null]},
{"id":"28109","county":"Pearl River County","measure":"so2","y1":1980,"y2":2021,"data":[null,null,null,null,null,null,null,null,null,null,null,null,null,null,null,null,null,null,null,null,null,null,null,null,null,null,null,null,null,null,null,null,null,null,null,null,null,null,null,null,null,null]},
{"id":"28109","county":"Pearl River County","measure":"no2","y1":1980,"y2":2021,"data":[null,null,null,null,null,null,null,null,null,null,null,null,null,null,null,null,null,null,null,null,null,null,null,null,null,null,null,null,null,null,null,null,null,null,null,null,null,null,null,null,null,null]},
{"id":"28109","county":"Pearl River County","measure":"co","y1":1980,"y2":2021,"data":[null,null,null,null,null,null,null,null,null,null,null,null,null,null,null,null,null,null,null,null,null,null,null,null,null,null,null,null,null,null,null,null,null,null,null,null,null,null,null,null,null,null]},
{"id":"28109","county":"Pearl River County","measure":"pm25","y1":1980,"y2":2021,"data":[null,null,null,null,null,null,null,null,null,null,null,null,null,null,null,null,null,null,null,null,43.2,42.5,44,39.1,37.1,40,null,null,null,null,null,null,null,null,null,null,null,null,null,null,null,null]},
{"id":"28109","county":"Pearl River County","measure":"pm10","y1":1980,"y2":2021,"data":[null,null,null,null,null,null,null,null,null,null,null,null,null,null,null,null,null,null,null,null,null,null,null,null,null,null,null,null,null,null,null,null,null,null,null,null,null,null,null,null,null,null]},
{"id":"28109","county":"Pearl River County","measure":"arsenic","y1":1980,"y2":2021,"data":[null,null,null,null,null,null,null,null,null,null,null,null,null,null,null,null,null,null,null,null,null,null,null,null,null,null,null,null,null,null,null,null,null,null,null,null,null,null,null,null,null,null]},
{"id":"28109","county":"Pearl River County","measure":"lead","y1":1980,"y2":2021,"data":[null,null,null,null,null,null,null,null,null,null,null,null,null,null,null,null,null,null,null,null,null,null,null,null,null,null,null,null,null,null,null,null,null,null,null,null,null,null,null,null,null,null]},
{"id":"28109","county":"Pearl River County","measure":"cadmium","y1":1980,"y2":2021,"data":[null,null,null,null,null,null,null,null,null,null,null,null,null,null,null,null,null,null,null,null,null,null,null,null,null,null,null,null,null,null,null,null,null,null,null,null,null,null,null,null,null,null]},
{"id":"28109","county":"Pearl River County","measure":"nickel","y1":1980,"y2":2021,"data":[null,null,null,null,null,null,null,null,null,null,null,null,null,null,null,null,null,null,null,null,null,null,null,null,null,null,null,null,null,null,null,null,null,null,null,null,null,null,null,null,null,null]}
]
