[
{"id":"47113","county":"Madison County","measure":"10green","y1":1980,"y2":2021,"data":[0,0,0,0,0,0,0,0,0,0,0,0,0,1,1,1,0,0,0,0,0,0,0,0,0,0,0,0,0,0,0,0,0,0,0,0,0,0,0,0,0,0]},
{"id":"47113","county":"Madison County","measure":"aqi","y1":1980,"y2":2021,"data":[null,null,null,null,null,null,32,31,28,27,26,25,27,36,42,34,19,19,23,51,53,51,42,24,17,34,43,45,14,11,15,14,null,33,34,32,28,27,26,27,25,28]},
{"id":"47113","county":"Madison County","measure":"ozone","y1":1980,"y2":2021,"data":[null,null,null,null,null,null,null,null,null,null,null,null,null,92.3,93.7,96.9,null,null,null,null,null,null,null,null,null,null,null,null,null,null,null,null,null,null,null,null,null,null,null,null,null,null]},
{"id":"47113","county":"Madison County","measure":"so2","y1":1980,"y2":2021,"data":[null,null,null,null,null,null,null,null,null,null,null,null,null,147.9,149.9,121.3,null,null,null,null,null,null,null,null,null,null,null,null,null,null,null,null,null,null,null,null,null,null,null,null,null,null]},
{"id":"47113","county":"Madison County","measure":"no2","y1":1980,"y2":2021,"data":[null,null,null,null,null,null,null,null,null,null,null,null,null,90.1,91.6,85.7,null,null,null,null,null,null,null,null,null,null,null,null,null,null,null,null,null,null,null,null,null,null,null,null,null,null]},
{"id":"47113","county":"Madison County","measure":"co","y1":1980,"y2":2021,"data":[null,null,null,null,null,null,null,null,null,null,null,null,null,null,null,null,null,null,null,null,null,null,null,null,null,null,null,null,null,null,null,null,null,null,null,null,null,null,null,null,null,null]},
{"id":"47113","county":"Madison County","measure":"pm25","y1":1980,"y2":2021,"data":[null,null,null,null,null,null,null,null,null,null,null,null,null,null,null,null,null,null,null,43,42.6,41.9,44,38.9,36.4,40,35.1,40.4,null,null,null,null,null,32.3,32.3,35.4,29.5,35.9,37.1,27.6,54.1,43.8]},
{"id":"47113","county":"Madison County","measure":"pm10","y1":1980,"y2":2021,"data":[null,null,null,null,null,null,107.4,93.1,95.4,95.8,91.1,89.2,78.7,75.5,76.8,80.8,85.5,78.6,80,86,100.3,118.8,110.9,150.1,98.3,89.9,134.1,121.4,103.5,111.5,101.4,137.8,null,null,null,null,null,null,null,null,null,null]},
{"id":"47113","county":"Madison County","measure":"arsenic","y1":1980,"y2":2021,"data":[null,null,null,null,null,null,null,null,null,null,null,null,null,null,null,null,null,null,null,null,null,null,null,null,null,null,null,null,null,null,null,null,null,null,null,null,null,null,null,null,null,null]},
{"id":"47113","county":"Madison County","measure":"lead","y1":1980,"y2":2021,"data":[null,null,null,null,null,null,null,null,null,null,null,null,null,null,null,null,1668.45,1179.15,993.01,null,null,null,null,null,null,null,null,null,null,null,null,null,null,null,null,null,null,null,null,null,null,null]},
{"id":"47113","county":"Madison County","measure":"cadmium","y1":1980,"y2":2021,"data":[null,null,null,null,null,null,null,null,null,null,null,null,null,null,null,null,null,null,null,null,null,null,null,null,null,null,null,null,null,null,null,null,null,null,null,null,null,null,null,null,null,null]},
{"id":"47113","county":"Madison County","measure":"nickel","y1":1980,"y2":2021,"data":[null,null,null,null,null,null,null,null,null,null,null,null,null,null,null,null,null,null,null,null,null,null,null,null,null,null,null,null,null,null,null,null,null,null,null,null,null,null,null,null,null,null]}
]
