[
{"id":"13185","county":"Lowndes County","measure":"aqi","y1":1980,"y2":2021,"data":[null,null,null,null,null,null,null,null,null,null,null,null,null,null,null,null,null,null,null,null,52,48,43,46,52,47,52,41,55,50,53,57,51,36,38,38,33,38,37,35,30,35]},
{"id":"13185","county":"Lowndes County","measure":"ozone","y1":1980,"y2":2021,"data":[null,null,null,null,null,null,null,null,null,null,null,null,null,null,null,null,null,null,null,null,null,null,null,null,null,null,null,null,null,null,null,null,null,null,null,null,null,null,null,null,null,null]},
{"id":"13185","county":"Lowndes County","measure":"so2","y1":1980,"y2":2021,"data":[null,null,null,null,null,null,null,null,null,null,null,null,null,null,null,null,null,null,null,null,null,null,null,null,null,null,null,null,null,null,null,null,null,null,null,null,null,null,null,null,null,null]},
{"id":"13185","county":"Lowndes County","measure":"no2","y1":1980,"y2":2021,"data":[null,null,null,null,null,null,null,null,null,null,null,null,null,null,null,null,null,null,null,null,null,null,null,null,null,null,null,null,null,null,null,null,null,null,null,null,null,null,null,null,null,null]},
{"id":"13185","county":"Lowndes County","measure":"no","y1":1980,"y2":2021,"data":[null,null,null,null,null,null,null,null,null,null,null,null,null,null,null,null,null,null,null,null,null,null,null,null,null,null,null,null,null,null,null,null,null,null,null,null,null,null,null,null,null,null]},
{"id":"13185","county":"Lowndes County","measure":"co","y1":1980,"y2":2021,"data":[null,null,null,null,null,null,null,null,null,null,null,null,null,null,null,null,null,null,null,null,null,null,null,null,null,null,null,null,null,null,null,null,null,null,null,null,null,null,null,null,null,null]},
{"id":"13185","county":"Lowndes County","measure":"pm25","y1":1980,"y2":2021,"data":[null,null,null,null,null,null,null,null,null,null,null,null,null,null,null,null,null,null,null,null,13.386700,12.561900,12.667800,11.696900,11.781200,11.492400,11.460800,11.830000,10.591700,9.837400,9.565000,9.809700,9.130200,9.340200,9.307600,8.807900,8.297000,8.922100,8.964600,7.764400,10.971500,9.172300]},
{"id":"13185","county":"Lowndes County","measure":"pm10","y1":1980,"y2":2021,"data":[null,null,null,null,null,null,null,null,null,null,null,null,null,null,null,null,null,null,null,null,null,null,null,null,null,null,null,null,null,null,null,null,null,null,null,null,null,null,null,null,null,null]},
{"id":"13185","county":"Lowndes County","measure":"arsenic","y1":1980,"y2":2021,"data":[null,null,null,null,null,null,null,null,null,null,null,null,null,null,null,null,null,null,null,null,null,null,null,0.001000,0.000600,0.001200,0.001400,0.000300,0.000500,null,null,null,null,null,null,null,null,null,null,null,null,null]},
{"id":"13185","county":"Lowndes County","measure":"lead","y1":1980,"y2":2021,"data":[null,null,null,null,null,null,null,0.104300,null,null,null,null,null,null,null,null,null,null,null,null,null,null,null,0.046100,0.062600,0.067000,0.042900,0.090700,0.127600,null,null,null,null,null,null,null,null,null,null,null,null,null]},
{"id":"13185","county":"Lowndes County","measure":"cadmium","y1":1980,"y2":2021,"data":[null,null,null,null,null,null,null,null,null,null,null,null,null,null,null,null,null,null,null,null,null,null,null,0.000500,0.000100,0.000200,0.000300,0.000100,0.000100,null,null,null,null,null,null,null,null,null,null,null,null,null]},
{"id":"13185","county":"Lowndes County","measure":"nickel","y1":1980,"y2":2021,"data":[null,null,null,null,null,null,null,null,null,null,null,null,null,null,null,null,null,null,null,null,null,null,null,0.005300,0.002100,0.002900,0.003300,0.000800,0.001500,null,null,null,null,null,null,null,null,null,null,null,null,null]},
{"id":"13185","county":"Lowndes County","measure":"10green","y1":1980,"y2":2021,"data":[null,null,null,null,null,null,null,null,null,null,null,null,null,null,null,null,null,null,null,null,4,4,3,3,4,5,3,3,5,5,6,6,5,4,3,3,3,4,4,4,2,2]}
]
