[
{"id":"23009","county":"Hancock County","measure":"aqi","y1":1980,"y2":2021,"data":[null,null,23,36,32,35,33,35,40,38,35,34,33,33,34,35,39,38,40,42,36,36,37,39,36,36,36,35,36,35,37,36,35,37,35,37,36,37,37,36,35,36]},
{"id":"23009","county":"Hancock County","measure":"ozone","y1":1980,"y2":2021,"data":[null,null,0.043200,0.045300,0.044300,0.045000,0.044200,0.046500,0.047800,0.044600,0.044000,0.044000,0.042300,0.042900,0.044000,0.045100,0.044500,0.044500,0.045800,0.047400,0.045000,0.044600,0.045900,0.044800,0.043500,0.045300,0.045700,0.046600,0.044800,0.042200,0.045200,0.045500,0.046500,0.043800,0.043500,0.043200,0.043200,0.043200,0.042900,0.042200,0.041200,0.042500]},
{"id":"23009","county":"Hancock County","measure":"so2","y1":1980,"y2":2021,"data":[null,null,null,null,null,null,null,null,22.580900,21.393400,20.546101,20.504499,null,null,null,null,null,null,null,null,null,null,null,null,11.858800,11.594500,10.841100,10.853100,13.533800,12.534100,14.470100,8.524700,9.150800,7.706700,7.948200,8.174600,8.122000,7.584300,6.624700,2.394500,2.456100,3.227400]},
{"id":"23009","county":"Hancock County","measure":"no2","y1":1980,"y2":2021,"data":[null,null,null,null,null,null,null,null,null,null,null,35.201401,null,null,null,null,30.722099,29.601299,29.960600,32.398399,30.305401,null,null,null,25.527000,25.433800,24.953600,24.211901,null,null,null,null,null,null,null,null,null,null,null,null,null,null]},
{"id":"23009","county":"Hancock County","measure":"no","y1":1980,"y2":2021,"data":[null,null,null,null,null,null,null,null,null,null,null,17.666800,null,null,null,null,13.956300,13.203700,13.298200,15.841700,14.756600,13.972100,12.944700,12.003000,10.858200,10.511900,9.650700,8.530000,7.959000,7.274500,6.074700,5.822200,5.505800,5.477600,5.333300,5.667300,5.000600,4.855900,4.411900,4.009500,3.872200,4.229400]},
{"id":"23009","county":"Hancock County","measure":"co","y1":1980,"y2":2021,"data":[null,null,null,null,null,null,null,null,null,null,1.056300,1.022300,null,null,null,null,null,null,null,null,null,null,0.657800,0.617300,0.569700,0.530200,0.503900,0.469900,0.440600,0.398500,0.389400,0.369400,0.363900,0.337000,0.331500,0.339000,0.333200,0.320600,0.312300,0.297200,0.313100,0.300300]},
{"id":"23009","county":"Hancock County","measure":"pm25","y1":1980,"y2":2021,"data":[null,null,null,null,null,null,null,null,null,null,null,null,null,null,null,null,null,null,null,null,null,null,null,null,null,null,null,null,null,null,null,null,null,9.338500,9.501100,8.942400,8.183200,8.566600,8.717900,7.724500,9.709500,8.968900]},
{"id":"23009","county":"Hancock County","measure":"pm10","y1":1980,"y2":2021,"data":[null,null,null,null,38.066200,40.249500,43.851002,36.526798,34.565498,null,null,null,null,null,null,26.521200,25.405001,25.703199,25.223200,null,null,null,null,null,null,null,null,null,null,null,23.348801,25.661900,25.920401,26.181299,28.290501,23.533899,25.498501,25.258600,25.342400,21.586000,27.317101,25.278799]},
{"id":"23009","county":"Hancock County","measure":"arsenic","y1":1980,"y2":2021,"data":[null,null,null,null,null,null,null,null,null,null,null,null,null,null,null,null,null,null,null,null,null,null,null,null,null,null,null,null,null,null,null,null,null,null,null,null,null,null,null,null,null,null]},
{"id":"23009","county":"Hancock County","measure":"lead","y1":1980,"y2":2021,"data":[null,null,null,null,null,null,null,null,null,null,null,null,null,null,null,null,null,null,null,null,null,null,null,null,null,null,null,null,null,null,null,null,null,null,null,null,null,null,null,null,null,null]},
{"id":"23009","county":"Hancock County","measure":"cadmium","y1":1980,"y2":2021,"data":[null,null,null,null,null,null,null,null,null,null,null,null,null,null,null,null,null,null,null,null,null,null,null,null,null,null,null,null,null,null,null,null,null,null,null,null,null,null,null,null,null,null]},
{"id":"23009","county":"Hancock County","measure":"nickel","y1":1980,"y2":2021,"data":[null,null,null,null,null,null,null,null,null,null,null,null,null,null,null,null,null,null,null,null,null,null,null,null,null,null,null,null,null,null,null,null,null,null,null,null,null,null,null,null,null,null]},
{"id":"23009","county":"Hancock County","measure":"10green","y1":1980,"y2":2021,"data":[null,null,1,2,2,2,2,2,2,2,2,2,2,2,3,3,3,3,4,3,3,3,2,3,3,3,2,3,3,3,4,3,3,4,3,3,4,4,4,4,3,2]}
]
