[
{"id":"42085","county":"Mercer County","measure":"aqi","y1":1980,"y2":2021,"data":[null,26,30,28,25,33,35,35,35,34,36,39,34,35,38,40,38,35,41,38,37,54,51,50,48,53,47,50,46,46,47,44,51,45,48,45,42,49,40,41,38,37]},
{"id":"42085","county":"Mercer County","measure":"ozone","y1":1980,"y2":2021,"data":[null,0.043400,0.043400,0.046100,0.044100,0.045200,0.044000,0.046300,0.048600,0.044600,0.044100,0.045500,0.042500,0.043600,0.045000,0.045800,0.045200,0.045500,0.047600,0.048000,0.045200,0.046100,0.047400,0.045300,0.043300,0.045900,0.045600,0.046600,0.044800,0.041900,0.045200,0.045000,0.046300,0.043300,0.042900,0.043000,0.043000,0.042700,0.042500,0.042000,0.040600,0.042100]},
{"id":"42085","county":"Mercer County","measure":"so2","y1":1980,"y2":2021,"data":[null,32.032200,30.959900,27.660900,28.860100,27.626900,26.263800,25.738701,25.011299,23.774300,22.738800,22.659100,20.123600,20.582600,19.740900,16.480900,16.007299,15.866000,15.777000,15.754400,14.700700,13.925300,12.803500,12.815600,12.150600,12.239900,11.013200,10.718100,11.632100,null,null,null,null,null,null,null,null,null,null,null,null,null]},
{"id":"42085","county":"Mercer County","measure":"no2","y1":1980,"y2":2021,"data":[null,null,null,null,null,null,null,null,null,null,null,null,null,null,null,null,null,null,null,null,null,null,null,null,null,null,null,null,null,null,null,null,null,null,null,null,null,null,null,null,null,null]},
{"id":"42085","county":"Mercer County","measure":"no","y1":1980,"y2":2021,"data":[null,null,null,null,null,null,null,null,null,null,null,null,null,null,null,null,null,null,null,null,null,null,null,null,null,null,null,null,null,null,null,null,null,null,null,null,null,null,null,null,null,null]},
{"id":"42085","county":"Mercer County","measure":"co","y1":1980,"y2":2021,"data":[null,null,null,null,null,null,null,null,null,null,null,null,null,null,null,null,null,null,null,null,null,null,null,null,null,null,null,null,null,null,null,null,null,null,null,null,null,null,null,null,null,null]},
{"id":"42085","county":"Mercer County","measure":"pm25","y1":1980,"y2":2021,"data":[null,null,null,null,null,null,null,null,null,null,null,null,null,null,null,null,null,null,null,null,13.334600,12.608400,12.366300,11.754900,11.542700,12.696600,11.447200,12.174300,10.636200,9.715800,9.958800,9.677400,9.221500,9.022300,8.984300,8.594300,7.801800,8.235600,8.261900,7.505500,8.668200,8.665700]},
{"id":"42085","county":"Mercer County","measure":"pm10","y1":1980,"y2":2021,"data":[null,null,null,null,null,41.401100,40.745602,36.114300,33.768299,32.694500,29.088600,28.874500,25.935400,25.490601,25.945900,24.950199,24.592300,24.268999,null,null,null,null,null,null,null,null,null,null,null,null,null,null,null,null,null,null,null,null,null,null,null,null]},
{"id":"42085","county":"Mercer County","measure":"arsenic","y1":1980,"y2":2021,"data":[null,null,null,null,null,null,null,null,null,null,null,null,null,null,null,null,null,null,null,null,null,null,null,null,null,null,null,null,null,null,null,null,null,null,null,null,null,null,null,null,null,null]},
{"id":"42085","county":"Mercer County","measure":"lead","y1":1980,"y2":2021,"data":[0.404900,0.324600,0.358300,null,null,null,null,null,null,null,null,0.204400,0.305400,0.313500,0.249900,0.228700,0.220600,0.152800,0.150700,null,null,null,null,null,null,null,null,null,null,null,null,null,null,null,null,null,null,null,null,null,null,null]},
{"id":"42085","county":"Mercer County","measure":"cadmium","y1":1980,"y2":2021,"data":[null,null,null,null,null,null,null,null,null,null,null,null,null,null,null,null,null,null,null,null,null,null,null,null,null,null,null,null,null,null,null,null,null,null,null,null,null,null,null,null,null,null]},
{"id":"42085","county":"Mercer County","measure":"nickel","y1":1980,"y2":2021,"data":[null,null,null,null,null,null,null,null,null,null,null,null,null,null,null,null,null,null,null,null,null,null,null,null,null,null,null,null,null,null,null,null,null,null,null,null,null,null,null,null,null,null]},
{"id":"42085","county":"Mercer County","measure":"10green","y1":1980,"y2":2021,"data":[null,1,1,1,1,2,2,2,2,2,3,3,2,2,3,3,3,3,4,3,3,4,4,4,4,5,3,4,4,4,5,4,5,5,4,4,5,5,4,5,3,3]}
]
