[
{"id":"48257","county":"Kaufman County","measure":"aqi","y1":1980,"y2":2021,"data":[null,null,null,null,null,null,null,null,null,null,null,46,null,null,null,null,null,null,null,null,27,39,35,38,36,47,46,43,44,43,42,45,44,42,40,37,37,39,35,39,37,36]},
{"id":"48257","county":"Kaufman County","measure":"ozone","y1":1980,"y2":2021,"data":[null,null,null,null,null,null,null,null,null,null,null,0.045400,null,null,null,null,null,null,null,null,0.045400,0.046100,0.047200,0.045200,0.043200,0.046000,0.045700,0.046800,0.044700,0.041700,0.045100,0.045000,0.046000,0.042900,0.042600,0.042500,0.042900,0.042400,0.042200,0.041900,0.040400,0.041800]},
{"id":"48257","county":"Kaufman County","measure":"so2","y1":1980,"y2":2021,"data":[null,null,null,null,null,null,null,null,null,null,null,null,null,null,null,null,null,null,null,null,14.649100,13.997800,12.740100,12.792200,12.131700,12.167300,10.982400,10.607700,11.173800,9.728000,10.296800,7.282300,6.826600,5.642300,5.676700,5.336300,5.054900,4.929900,4.486900,2.869400,2.614100,3.157400]},
{"id":"48257","county":"Kaufman County","measure":"no2","y1":1980,"y2":2021,"data":[null,null,null,null,null,null,null,null,null,null,null,null,null,null,null,null,null,null,null,null,28.224100,28.039200,26.825399,25.750900,24.090500,24.448200,23.377701,22.791401,21.915001,19.987000,19.457701,19.514900,18.877199,18.221201,18.514200,18.362499,17.746000,17.292700,17.089500,16.705200,16.139200,16.598000]},
{"id":"48257","county":"Kaufman County","measure":"no","y1":1980,"y2":2021,"data":[null,null,null,null,null,null,null,null,null,null,null,null,null,null,null,null,null,null,null,null,12.825200,12.483900,11.288100,10.340800,9.203400,8.961300,8.120200,7.310600,6.391700,5.708800,5.046600,5.072100,4.781100,4.588600,4.875300,5.145100,4.541000,4.218100,4.094200,3.732600,3.502700,3.780000]},
{"id":"48257","county":"Kaufman County","measure":"co","y1":1980,"y2":2021,"data":[null,null,null,null,null,null,null,null,null,null,null,null,null,null,null,null,null,null,null,null,null,null,null,null,null,null,null,null,null,null,null,null,null,null,null,null,null,null,null,null,null,null]},
{"id":"48257","county":"Kaufman County","measure":"pm25","y1":1980,"y2":2021,"data":[null,null,null,null,null,null,null,null,null,null,null,null,null,null,null,null,null,null,null,null,null,null,12.324500,11.822800,11.622700,12.706100,null,null,null,null,null,null,null,null,null,null,null,null,null,null,null,null]},
{"id":"48257","county":"Kaufman County","measure":"pm10","y1":1980,"y2":2021,"data":[null,null,null,null,null,null,null,null,null,null,null,null,null,null,null,null,null,null,null,null,null,null,null,null,null,null,null,null,null,null,null,null,null,null,null,null,null,null,null,null,null,null]},
{"id":"48257","county":"Kaufman County","measure":"arsenic","y1":1980,"y2":2021,"data":[null,null,null,null,null,null,null,null,null,null,null,null,null,null,null,null,null,null,null,null,null,null,null,null,null,null,null,null,null,null,null,null,null,null,null,null,null,null,null,null,null,null]},
{"id":"48257","county":"Kaufman County","measure":"lead","y1":1980,"y2":2021,"data":[null,null,null,null,null,null,null,null,null,null,null,null,0.298000,0.301700,0.246800,0.234200,0.226400,null,null,null,null,null,null,null,null,null,null,null,null,null,null,0.063700,0.051100,0.037200,0.020200,0.017500,null,null,0.023600,0.021200,0.017300,0.017700]},
{"id":"48257","county":"Kaufman County","measure":"cadmium","y1":1980,"y2":2021,"data":[null,null,null,null,null,null,null,null,null,null,null,null,null,null,null,null,null,null,null,null,null,null,null,null,null,null,null,null,null,null,null,null,null,null,null,null,null,null,null,null,null,null]},
{"id":"48257","county":"Kaufman County","measure":"nickel","y1":1980,"y2":2021,"data":[null,null,null,null,null,null,null,null,null,null,null,null,null,null,null,null,null,null,null,null,null,null,null,null,null,null,null,null,null,null,null,null,null,null,null,null,null,null,null,null,null,null]},
{"id":"48257","county":"Kaufman County","measure":"10green","y1":1980,"y2":2021,"data":[null,null,null,null,null,null,null,null,null,null,null,3,null,null,null,null,null,null,null,null,2,3,2,3,3,5,3,3,4,4,4,4,4,4,4,3,4,4,3,4,3,2]}
]
