[
{"id":"51139","county":"Page County","measure":"aqi","y1":1980,"y2":2021,"data":[null,null,null,null,null,null,null,null,null,null,null,null,null,null,null,null,null,null,null,50,47,51,47,45,43,49,47,46,45,40,46,42,44,39,40,42,null,null,null,null,null,null]},
{"id":"51139","county":"Page County","measure":"ozone","y1":1980,"y2":2021,"data":[null,null,null,null,null,null,null,null,null,null,null,null,null,null,null,null,null,null,null,0.048400,0.045800,0.046300,0.047400,0.045700,0.043400,0.046300,0.046000,0.047100,0.044900,0.041800,0.045200,0.045200,0.046200,0.043200,0.042800,0.042700,null,null,null,null,null,null]},
{"id":"51139","county":"Page County","measure":"so2","y1":1980,"y2":2021,"data":[null,null,null,null,null,null,null,null,null,null,null,null,null,null,null,null,null,null,null,null,null,null,null,null,null,null,null,null,null,null,null,null,null,null,null,null,null,null,null,null,null,null]},
{"id":"51139","county":"Page County","measure":"no2","y1":1980,"y2":2021,"data":[null,null,null,null,null,null,null,null,null,null,null,null,null,null,null,null,null,null,null,null,null,null,null,null,null,null,null,null,null,null,null,null,null,null,null,null,null,null,null,null,null,null]},
{"id":"51139","county":"Page County","measure":"no","y1":1980,"y2":2021,"data":[null,null,null,null,null,null,null,null,null,null,null,null,null,null,null,null,null,null,null,null,null,null,null,null,null,null,null,null,null,null,null,null,null,null,null,null,null,null,null,null,null,null]},
{"id":"51139","county":"Page County","measure":"co","y1":1980,"y2":2021,"data":[null,null,null,null,null,null,null,null,null,null,null,null,null,null,null,null,null,null,null,null,null,null,null,null,null,null,null,null,null,null,null,null,null,null,null,null,null,null,null,null,null,null]},
{"id":"51139","county":"Page County","measure":"pm25","y1":1980,"y2":2021,"data":[null,null,null,null,null,null,null,null,null,null,null,null,null,null,null,null,null,null,null,13.537800,13.338900,12.584200,12.296600,11.742800,11.618200,12.600400,11.471700,12.140500,10.568400,9.698800,9.930000,9.699900,9.196800,9.075300,8.925400,8.519700,null,null,null,null,null,null]},
{"id":"51139","county":"Page County","measure":"pm10","y1":1980,"y2":2021,"data":[null,null,null,null,null,null,null,null,null,null,null,null,null,null,null,null,null,null,null,null,null,null,null,null,null,null,null,null,null,null,null,null,null,null,null,null,null,null,null,null,null,null]},
{"id":"51139","county":"Page County","measure":"arsenic","y1":1980,"y2":2021,"data":[0.018800,0.028100,0.013600,null,null,null,null,null,null,null,null,null,null,null,null,null,null,null,null,null,null,null,null,null,null,null,null,null,null,null,null,null,null,null,null,null,null,null,null,null,null,null]},
{"id":"51139","county":"Page County","measure":"lead","y1":1980,"y2":2021,"data":[0.388700,0.312500,0.361900,null,null,null,null,null,null,null,null,null,null,null,null,null,null,null,null,null,null,null,null,null,null,null,null,null,null,null,null,null,null,null,null,null,null,null,null,null,null,null]},
{"id":"51139","county":"Page County","measure":"cadmium","y1":1980,"y2":2021,"data":[0.010500,0.014800,0.006800,null,null,null,null,null,null,null,null,null,null,null,null,null,null,null,null,null,null,null,null,null,null,null,null,null,null,null,null,null,null,null,null,null,null,null,null,null,null,null]},
{"id":"51139","county":"Page County","measure":"nickel","y1":1980,"y2":2021,"data":[0.006800,0.005400,0.006500,null,null,null,null,null,null,null,null,null,null,null,null,null,null,null,null,null,null,null,null,null,null,null,null,null,null,null,null,null,null,null,null,null,null,null,null,null,null,null]},
{"id":"51139","county":"Page County","measure":"10green","y1":1980,"y2":2021,"data":[null,null,null,null,null,null,null,null,null,null,null,null,null,null,null,null,null,null,null,4,4,4,3,3,3,5,3,4,4,4,5,4,4,4,4,4,null,null,null,null,null,null]}
]
