[
{"id":"55123","county":"Vernon County","measure":"aqi","y1":1980,"y2":2021,"data":[null,null,null,8,9,null,null,null,null,19,39,38,31,33,35,36,36,39,42,40,40,41,43,46,37,44,43,42,40,36,39,null,null,null,null,null,null,null,null,null,null,null]},
{"id":"55123","county":"Vernon County","measure":"ozone","y1":1980,"y2":2021,"data":[null,null,null,null,null,null,null,null,null,null,0.044500,0.045600,0.042600,0.043900,0.045200,0.046200,0.045300,0.045700,0.047900,0.048200,0.045600,0.046200,0.047300,0.045600,0.043200,0.046100,0.045900,0.046900,0.044800,0.041700,0.045000,null,null,null,null,null,null,null,null,null,null,null]},
{"id":"55123","county":"Vernon County","measure":"so2","y1":1980,"y2":2021,"data":[32.214401,32.065201,30.626400,28.035700,29.360500,27.779499,null,null,null,null,null,null,null,null,null,null,null,null,null,null,null,null,null,null,null,null,null,null,null,null,null,null,null,null,null,null,null,null,null,null,null,null]},
{"id":"55123","county":"Vernon County","measure":"no2","y1":1980,"y2":2021,"data":[null,null,null,38.846100,38.658401,null,null,null,null,null,null,null,null,null,null,null,null,null,null,null,null,null,null,null,null,null,null,null,null,null,null,null,null,null,null,null,null,null,null,null,null,null]},
{"id":"55123","county":"Vernon County","measure":"no","y1":1980,"y2":2021,"data":[null,null,null,18.784599,19.884701,null,null,null,null,null,null,null,null,null,null,null,null,null,null,null,null,null,null,null,null,null,null,null,null,null,null,null,null,null,null,null,null,null,null,null,null,null]},
{"id":"55123","county":"Vernon County","measure":"co","y1":1980,"y2":2021,"data":[null,null,null,null,null,null,null,null,null,null,null,null,null,null,null,null,null,null,null,null,null,null,null,null,null,null,null,null,null,null,null,null,null,null,null,null,null,null,null,null,null,null]},
{"id":"55123","county":"Vernon County","measure":"pm25","y1":1980,"y2":2021,"data":[null,null,null,null,null,null,null,null,null,null,null,null,null,null,null,null,null,null,null,null,null,null,null,null,null,null,null,null,null,null,null,null,null,null,null,null,null,null,null,null,null,null]},
{"id":"55123","county":"Vernon County","measure":"pm10","y1":1980,"y2":2021,"data":[null,null,null,null,null,null,null,null,null,32.739799,29.155800,29.127199,26.185301,25.835899,26.003401,24.983700,24.798100,24.583599,24.842800,25.563400,null,null,null,null,null,null,null,null,null,null,null,null,null,null,null,null,null,null,null,null,null,null]},
{"id":"55123","county":"Vernon County","measure":"arsenic","y1":1980,"y2":2021,"data":[null,null,null,null,null,null,null,null,null,null,null,null,null,null,null,null,null,null,null,null,null,null,null,null,null,null,null,null,null,null,null,null,null,null,null,null,null,null,null,null,null,null]},
{"id":"55123","county":"Vernon County","measure":"lead","y1":1980,"y2":2021,"data":[null,null,null,null,null,null,null,null,null,null,null,null,null,null,null,null,null,null,null,null,null,null,null,null,null,null,null,null,null,null,null,null,null,null,null,null,null,null,null,null,null,null]},
{"id":"55123","county":"Vernon County","measure":"cadmium","y1":1980,"y2":2021,"data":[null,null,null,null,null,null,null,null,null,null,null,null,null,null,null,null,null,null,null,null,null,null,null,null,null,null,null,null,null,null,null,null,null,null,null,null,null,null,null,null,null,null]},
{"id":"55123","county":"Vernon County","measure":"nickel","y1":1980,"y2":2021,"data":[null,null,null,null,null,null,null,null,null,null,null,null,null,null,null,null,null,null,null,null,null,null,null,null,null,null,null,null,null,null,null,null,null,null,null,null,null,null,null,null,null,null]},
{"id":"55123","county":"Vernon County","measure":"10green","y1":1980,"y2":2021,"data":[null,null,null,0,0,null,null,null,null,1,3,3,2,2,3,3,3,4,4,3,3,3,3,3,3,4,3,3,3,3,4,null,null,null,null,null,null,null,null,null,null,null]}
]
